aasm/__init__.py
aasm/translate.py
aasm/generating/__init__.py
aasm/generating/code.py
aasm/generating/python_code.py
aasm/generating/python_graph.py
aasm/generating/python_module.py
aasm/generating/python_spade.py
aasm/intermediate/__init__.py
aasm/intermediate/action.py
aasm/intermediate/agent.py
aasm/intermediate/argument.py
aasm/intermediate/behaviour.py
aasm/intermediate/block.py
aasm/intermediate/declaration.py
aasm/intermediate/graph.py
aasm/intermediate/instruction.py
aasm/intermediate/message.py
aasm/intermediate/module.py
aasm/modules/__init__.py
aasm/modules/instruction.py
aasm/modules/module.py
aasm/modules/type.py
aasm/parsing/__init__.py
aasm/parsing/parse.py
aasm/parsing/state.py
aasm/parsing/op/__init__.py
aasm/parsing/op/action.py
aasm/parsing/op/agent.py
aasm/parsing/op/behav.py
aasm/parsing/op/clr.py
aasm/parsing/op/conditional.py
aasm/parsing/op/decl.py
aasm/parsing/op/defg.py
aasm/parsing/op/defnode.py
aasm/parsing/op/deftype.py
aasm/parsing/op/eblock.py
aasm/parsing/op/graph.py
aasm/parsing/op/len.py
aasm/parsing/op/list_inclusion.py
aasm/parsing/op/list_modification.py
aasm/parsing/op/logs.py
aasm/parsing/op/lr.py
aasm/parsing/op/lw.py
aasm/parsing/op/math.py
aasm/parsing/op/math_exp.py
aasm/parsing/op/math_mod.py
aasm/parsing/op/message.py
aasm/parsing/op/module.py
aasm/parsing/op/mparams.py
aasm/parsing/op/prm.py
aasm/parsing/op/rand.py
aasm/parsing/op/remen.py
aasm/parsing/op/round.py
aasm/parsing/op/scale.py
aasm/parsing/op/send.py
aasm/parsing/op/set.py
aasm/parsing/op/size.py
aasm/parsing/op/subs.py
aasm/parsing/op/types.py
aasm/preprocessor/__init__.py
aasm/preprocessor/constant.py
aasm/preprocessor/macro.py
aasm/preprocessor/preprocessor.py
aasm/preprocessor/preprocessor_item.py
aasm/tests/__init__.py
aasm/tests/conftest.py
aasm/tests/test_graph_generation.py
aasm/tests/fixtures/barabasi-albert.aasm
aasm/tests/fixtures/inhomogenous.aasm
aasm/tests/fixtures/matrix.aasm
aasm/tests/fixtures/statistical.aasm
aasm/utils/__init__.py
aasm-0.1.8.dist-info/LICENSE.md
aasm-0.1.8.dist-info/WHEEL
aasm-0.1.8.dist-info/METADATA
aasm-0.1.8.dist-info/RECORD
