Metadata-Version: 2.1
Name: aasm
Version: 0.1.8
Summary: Agents Assembly translator
Keywords: aasm,agents assembly,agents,translator,dsl,domain specific language,simulations
Requires-Python: >=3.10
Project-URL: Documentation, https://agents-assembly.com/docs
Project-URL: Source, https://github.com/agent-based-information-flow-simulation/agents-assembly-translator
